{
    "/js/app.js": "/js/app.js?id=3ccaccf01c71530f56df",
    "/js/livewire-handler.js": "/js/livewire-handler.js?id=722402b8823c179800c1",
    "/js/editor.js": "/js/editor.js?id=7f31d740bc75e0895b6a",
    "/js/aos.js": "/js/aos.js?id=fa8c8489e683221f0bf4",
    "/js/swiper.js": "/js/swiper.js?id=700e8cfba7a45e889b7d",
    "/js/viewer.js": "/js/viewer.js?id=4a1083caa942f265ff7c",
    "/css/app.css": "/css/app.css?id=0e6b5de229f662229ad8",
    "/css/chat.css": "/css/chat.css?id=d27448cf7c1e7b4b9adb"
}
